quadro/__init__.py
quadro/verify_imu.py
quadro/base/__init__.py
quadro/base/auxillary/__init__.py
quadro/base/auxillary/dplot.py
quadro/base/auxillary/rotation.py
quadro/base/auxillary/rpy.py
quadro/base/deepl/__init__.py
quadro/base/deepl/deepl_kin.py
quadro/base/dynamics/__init__.py
quadro/base/imu/__init__.py
quadro/base/imu/load_imu.py
quadro/base/kinematics/__init__.py
quadro/base/kinematics/kinematics.py
quadro/base/trajectory/__init__.py
quadro/base/trajectory/bezier_no_numpy.py
quadro/base/trajectory/bezier_no_numpy_stairs.py
quadro/base/trajectory/new_bezier.py
quadro/base/trajectory/tri_bezier.py
quadro-1.0.0.dist-info/METADATA
quadro-1.0.0.dist-info/WHEEL
quadro-1.0.0.dist-info/top_level.txt
quadro-1.0.0.dist-info/RECORD
