Metadata-Version: 2.1
Name: quadro
Version: 1.0.0
Summary: A quad package
Home-page: https://github.com/2vin2vin/quadro.git
Author: 2vin2vin
Author-email: sohithvulpie@gmail.com
Classifier: Programming Language :: Python :: 3
Classifier: License :: OSI Approved :: MIT License
Classifier: Operating System :: OS Independent
